disnowflake/__init__.py
disnowflake/disnowflake.py
disnowflake-1.2.0.dist-info/LICENSE
disnowflake-1.2.0.dist-info/METADATA
disnowflake-1.2.0.dist-info/WHEEL
disnowflake-1.2.0.dist-info/top_level.txt
disnowflake-1.2.0.dist-info/RECORD
