Metadata-Version: 2.1
Name: disnowflake
Version: 1.2.0
Summary: Discord snowflake changer
Home-page: https://github.com/peco2282/disnowflake
Author: peco2282
Author-email: pecop2282@gmail.com
License: MIT
Requires-Python: >=3.8.0
License-File: LICENSE
